powpow/__init__.py
powpow/_backports.py
powpow/unixy.py
powpow/version.py
powpow-0.0.4.dist-info/METADATA
powpow-0.0.4.dist-info/WHEEL
powpow-0.0.4.dist-info/top_level.txt
powpow-0.0.4.dist-info/RECORD
